LICENSE.rst
MANIFEST.in
README.rst
setup.cfg
setup.py
dtool_ecs/__init__.py
dtool_ecs/storagebroker.py
dtool_ecs.egg-info/PKG-INFO
dtool_ecs.egg-info/SOURCES.txt
dtool_ecs.egg-info/dependency_links.txt
dtool_ecs.egg-info/entry_points.txt
dtool_ecs.egg-info/requires.txt
dtool_ecs.egg-info/top_level.txt