Metadata-Version: 1.1
Name: dtool-ecs
Version: 0.3.1
Summary: Add ECS S3 support to dtool
Home-page: https://github.com/jic-dtool/dtool-ecs
Author: Tjelvar Olsson
Author-email: tjelvar.olsson@jic.ac.uk
License: MIT
Download-URL: https://github.com/jic-dtool/dtool-ecs/tarball/0.3.1
Platform: UNKNOWN
